dayu_ffmpeg/__init__.py
dayu_ffmpeg/base.py
dayu_ffmpeg/config.py
dayu_ffmpeg/error.py
dayu_ffmpeg/ffscript.py
dayu_ffmpeg/stream.py
dayu_ffmpeg/util.py
dayu_ffmpeg-0.5.dist-info/METADATA
dayu_ffmpeg-0.5.dist-info/RECORD
dayu_ffmpeg-0.5.dist-info/WHEEL
dayu_ffmpeg-0.5.dist-info/top_level.txt
