Metadata-Version: 2.1
Name: dayu-ffmpeg
Version: 0.5
Summary: FFmpeg python wrapper for human, with common filters built in.
Home-page: https://github.com/phenom-films/dayu_ffmpeg
Author: andyguo
Author-email: andyguo@phenom-films.com
License: MIT
Platform: UNKNOWN
Classifier: Operating System :: OS Independent
Classifier: Programming Language :: Python
Classifier: Programming Language :: Python :: Implementation
Classifier: Programming Language :: Python :: 2
Classifier: Programming Language :: Python :: 2.7
